{"name":"Welcome to my website","tagline":"Akshith R Kandakatla","body":"### Welcome to GitHub Pages.\r\nhttps://media.licdn.com/media/AAEAAQAAAAAAAASEAAAAJDIyYjg0ZDY1LTUzZTAtNDllYi04NTU2LTUzYzI5ZTY2N2U5NA.jpg\r\n\r\nI'm a Masters in Computer Information Systems from Boston University. I am a Data Analytics/Science enthusiast.\r\n\r\nWhile pursuing my Masters, during the summer break of 2015 I enrolled in the Udacity's Data Analyst Nanodegree MOOC. I interacted with similar enthusiasts from across the globe through udacity's blog and worked on several Analytics projects as well as helped others overcome their obstacles analyzing data.\r\n\r\n\r\n<a href=\"mailto:rosshanabshetty@gmail.com\">Email Me</a>\r\n<a href=\"https://github.com/akshithrk\">Github</a>\r\n","google":"","note":"Don't delete this file! It's used internally to help with page regeneration."}